dbkp/__init__.py
dbkp/__main__.py
dbkp/dbkp.py
dbkp-1.0.5.dist-info/LICENSE
dbkp-1.0.5.dist-info/METADATA
dbkp-1.0.5.dist-info/WHEEL
dbkp-1.0.5.dist-info/entry_points.txt
dbkp-1.0.5.dist-info/RECORD
