Metadata-Version: 2.1
Name: dbkp
Version: 1.0.5
Summary: Dotfiles backup and restore tool
Home-page: https://github.com/acristoffers/dbkp
License: MIT
Keywords: dotfiles,backup,restore,manager
Author: Álan Crístoffer
Author-email: acristoffers@startmail.com
Requires-Python: >=3.7
Classifier: License :: OSI Approved :: MIT License
Classifier: Programming Language :: Python :: 3
Classifier: Programming Language :: Python :: 3.7
Classifier: Programming Language :: Python :: 3.8
Classifier: Programming Language :: Python :: 3.9
Classifier: Programming Language :: Python :: 3.10
Classifier: Programming Language :: Python :: 3.11
Classifier: Programming Language :: Python :: 3.12
Requires-Dist: pydantic (>=2.5.2,<3.0.0)
Project-URL: Repository, https://github.com/acristoffers/dbkp
